[{"city":"","icon_avatar":"http:\/\/img3.douban.com\/icon\/ui65276977-4.jpg","statuses_count":130,"screen_name":"猪头小秘书","following_count":27,"url":"http:\/\/www.douban.com\/people\/65276977\/","created_at":"2012-10-10 12:15:55","description":"","is_first_visit":true,"new_site_to_vu_count":0,"followers_count":146,"location":"","small_avatar":"http:\/\/img3.douban.com\/icon\/u65276977-4.jpg","following":false,"verified":false,"large_avatar":"http:\/\/img3.douban.com\/icon\/ul65276977-4.jpg","type":"user","id":"65276977","uid":"zhutousecretary"},{"city":"","icon_avatar":"http:\/\/img3.douban.com\/icon\/ui2683441-49.jpg","statuses_count":1416,"screen_name":"Soe.pdf","following_count":387,"url":"http:\/\/www.douban.com\/people\/2683441\/","created_at":"2008-07-09 20:37:48","description":"","is_first_visit":false,"new_site_to_vu_count":40,"followers_count":190,"location":"","small_avatar":"http:\/\/img3.douban.com\/icon\/u2683441-49.jpg","following":false,"verified":false,"large_avatar":"http:\/\/img3.douban.com\/icon\/ul2683441-49.jpg","type":"user","id":"2683441","uid":"marsnayoko"},{"city":"","icon_avatar":"http:\/\/img3.douban.com\/icon\/ui54593803-49.jpg","statuses_count":1007,"screen_name":"成于思","following_count":88,"url":"http:\/\/www.douban.com\/people\/54593803\/","created_at":"2011-09-23 19:14:54","description":"","is_first_visit":true,"new_site_to_vu_count":0,"followers_count":49,"location":"","small_avatar":"http:\/\/img3.douban.com\/icon\/u54593803-49.jpg","following":false,"verified":false,"large_avatar":"http:\/\/img3.douban.com\/icon\/ul54593803-49.jpg","type":"user","id":"54593803","uid":"Yepupyale"},{"city":"","icon_avatar":"http:\/\/img3.douban.com\/icon\/ui1176229-2.jpg","statuses_count":2453,"screen_name":"Menghan","following_count":623,"url":"http:\/\/www.douban.com\/people\/1176229\/","created_at":"2006-05-25 19:11:38","description":"","is_first_visit":false,"new_site_to_vu_count":6,"followers_count":384,"location":"","small_avatar":"http:\/\/img3.douban.com\/icon\/u1176229-2.jpg","following":false,"verified":false,"large_avatar":"http:\/\/img3.douban.com\/icon\/ul1176229-2.jpg","type":"user","id":"1176229","uid":"thuskyblue"},{"city":"","icon_avatar":"http:\/\/img3.douban.com\/icon\/ui42754762-74.jpg","statuses_count":674,"screen_name":"圆脸不好办QAQ","following_count":89,"url":"http:\/\/www.douban.com\/people\/42754762\/","created_at":"2010-06-28 19:38:28","description":"","is_first_visit":true,"new_site_to_vu_count":0,"followers_count":75,"location":"","small_avatar":"http:\/\/img3.douban.com\/icon\/u42754762-74.jpg","following":false,"verified":false,"large_avatar":"http:\/\/img3.douban.com\/icon\/ul42754762-74.jpg","type":"user","id":"42754762","uid":"cam1lla"},{"city":"","icon_avatar":"http:\/\/img3.douban.com\/icon\/ui52627161-2.jpg","statuses_count":18,"screen_name":"Tom","following_count":5,"url":"http:\/\/www.douban.com\/people\/52627161\/","created_at":"2011-06-26 11:12:08","description":"","is_first_visit":true,"new_site_to_vu_count":0,"followers_count":3,"location":"","small_avatar":"http:\/\/img3.douban.com\/icon\/u52627161-2.jpg","following":false,"verified":false,"large_avatar":"http:\/\/img3.douban.com\/icon\/ul52627161-2.jpg","type":"user","id":"52627161","uid":"tom21joy"},{"city":"","icon_avatar":"http:\/\/img3.douban.com\/icon\/ui30323883-2.jpg","statuses_count":71,"screen_name":"伤感熊","following_count":7,"url":"http:\/\/www.douban.com\/people\/30323883\/","created_at":"2009-12-25 20:07:34","description":"SA, SEOer, 关注用户体验。","is_first_visit":false,"new_site_to_vu_count":0,"followers_count":4,"location":"","small_avatar":"http:\/\/img3.douban.com\/icon\/u30323883-2.jpg","following":false,"verified":false,"large_avatar":"http:\/\/img3.douban.com\/icon\/ul30323883-2.jpg","type":"user","id":"30323883","uid":"sk23"},{"city":"","icon_avatar":"http:\/\/img3.douban.com\/icon\/ui3815688-75.jpg","statuses_count":1901,"screen_name":"Wyapples.bin","following_count":168,"url":"http:\/\/www.douban.com\/people\/3815688\/","created_at":"2009-03-15 20:23:26","description":"大学生。 \n自由软件Fans。 \n不懂摄影，只是个按快门的，看心情放快门。 \n摇滚，不成形的BASS手兼小提琴手。 \nMore:http:\/\/goo.gl\/z7Yus","is_first_visit":false,"new_site_to_vu_count":3,"followers_count":147,"location":"","small_avatar":"http:\/\/img3.douban.com\/icon\/u3815688-75.jpg","following":false,"verified":false,"large_avatar":"http:\/\/img3.douban.com\/icon\/ul3815688-75.jpg","type":"user","id":"3815688","uid":"wyapples"},{"uid":"900036201","following_count":0,"flag_icon":"http:\/\/img3.douban.com\/anduin\/pics\/va-icon-site.png","agents":[],"id":"900036201","is_first_visit":true,"city":"","verified":false,"followers_count":1693,"location":"","show_agent":false,"type":"virtual","large_avatar":"http:\/\/img3.douban.com\/view\/site\/large\/public\/400225c23e6da2c.jpg","icon_avatar":"http:\/\/img3.douban.com\/pics\/icon\/user_icon.jpg","statuses_count":30,"description":"","screen_name":"時光機°","url":"","created_at":"2012-01-07 18:17:45","original_site_url":"http:\/\/site.douban.com\/Time_Machine\/","small_avatar":"http:\/\/img3.douban.com\/view\/site\/small\/public\/4a0561dd32f6586.jpg","following":false},{"city":"","icon_avatar":"http:\/\/img3.douban.com\/icon\/ui64054630-2.jpg","statuses_count":4,"screen_name":"小妮子","following_count":9,"url":"http:\/\/www.douban.com\/people\/64054630\/","created_at":"2012-08-21 14:07:42","description":"","is_first_visit":true,"new_site_to_vu_count":0,"followers_count":5,"location":"","small_avatar":"http:\/\/img3.douban.com\/icon\/u64054630-2.jpg","following":false,"verified":false,"large_avatar":"http:\/\/img3.douban.com\/icon\/ul64054630-2.jpg","type":"user","id":"64054630","uid":"64054630"},{"uid":"900077827","following_count":0,"flag_icon":"http:\/\/img3.douban.com\/anduin\/pics\/va-icon-site.png","agents":[],"id":"900077827","is_first_visit":true,"city":"","verified":false,"followers_count":8,"location":"","show_agent":false,"type":"virtual","large_avatar":"http:\/\/img3.douban.com\/view\/site\/large\/public\/ae455dbb9e1e31d.jpg","icon_avatar":"http:\/\/img3.douban.com\/pics\/icon\/user_icon.jpg","statuses_count":20,"description":"","screen_name":"米泥花圃","url":"","created_at":"2012-08-24 14:18:06","original_site_url":"http:\/\/site.douban.com\/178591\/","small_avatar":"http:\/\/img3.douban.com\/view\/site\/small\/public\/2ff8f5fb813e8d7.jpg","following":false},{"city":"","icon_avatar":"http:\/\/img3.douban.com\/icon\/ui2190815-2.jpg","statuses_count":213,"screen_name":"功夫","following_count":50,"url":"http:\/\/www.douban.com\/people\/2190815\/","created_at":"2008-01-24 10:38:41","description":"点燃火焰","is_first_visit":false,"new_site_to_vu_count":0,"followers_count":21,"location":"","small_avatar":"http:\/\/img3.douban.com\/icon\/u2190815-2.jpg","following":false,"verified":false,"large_avatar":"http:\/\/img3.douban.com\/icon\/ul2190815-2.jpg","type":"user","id":"2190815","uid":"zzqr"},{"city":"","icon_avatar":"http:\/\/img3.douban.com\/icon\/ui53506107-28.jpg","statuses_count":767,"screen_name":"yali66变腐前","following_count":354,"url":"http:\/\/www.douban.com\/people\/53506107\/","created_at":"2011-08-02 17:47:29","description":"","is_first_visit":false,"new_site_to_vu_count":4,"followers_count":271,"location":"","small_avatar":"http:\/\/img3.douban.com\/icon\/u53506107-28.jpg","following":false,"verified":false,"large_avatar":"http:\/\/img3.douban.com\/icon\/ul53506107-28.jpg","type":"user","id":"53506107","uid":"yali66"},{"city":"","icon_avatar":"http:\/\/img3.douban.com\/icon\/ui57349650-8.jpg","statuses_count":1315,"screen_name":"柔晋上行","following_count":118,"url":"http:\/\/www.douban.com\/people\/57349650\/","created_at":"2011-12-28 11:03:27","description":"","is_first_visit":false,"new_site_to_vu_count":0,"followers_count":36,"location":"","small_avatar":"http:\/\/img3.douban.com\/icon\/u57349650-8.jpg","following":false,"verified":false,"large_avatar":"http:\/\/img3.douban.com\/icon\/ul57349650-8.jpg","type":"user","id":"57349650","uid":"57349650"},{"city":"","icon_avatar":"http:\/\/img3.douban.com\/icon\/ui13259704-34.jpg","statuses_count":1207,"screen_name":"凤凰205","following_count":166,"url":"http:\/\/www.douban.com\/people\/13259704\/","created_at":"2009-09-24 13:37:03","description":"！@#￥%……&","is_first_visit":false,"new_site_to_vu_count":4,"followers_count":70,"location":"","small_avatar":"http:\/\/img3.douban.com\/icon\/u13259704-34.jpg","following":false,"verified":false,"large_avatar":"http:\/\/img3.douban.com\/icon\/ul13259704-34.jpg","type":"user","id":"13259704","uid":"nonoku"},{"uid":"900020456","following_count":0,"flag_icon":"http:\/\/img3.douban.com\/anduin\/pics\/va-icon-site.png","agents":[],"id":"900020456","is_first_visit":true,"city":"","verified":false,"followers_count":242,"location":"","show_agent":false,"type":"virtual","large_avatar":"http:\/\/img3.douban.com\/view\/site\/large\/public\/600aee7264a612b.jpg","icon_avatar":"http:\/\/img3.douban.com\/pics\/icon\/user_icon.jpg","statuses_count":51,"description":"","screen_name":"javascript","url":"","created_at":"2012-01-07 18:03:36","original_site_url":"http:\/\/site.douban.com\/138910\/","small_avatar":"http:\/\/img3.douban.com\/view\/site\/small\/public\/7e201fd6f51146c.jpg","following":false},{"city":"","icon_avatar":"http:\/\/img3.douban.com\/icon\/ui2191713-36.jpg","statuses_count":765,"screen_name":"麦麦小茶","following_count":113,"url":"http:\/\/www.douban.com\/people\/2191713\/","created_at":"2008-01-24 16:47:54","description":"无良动画师。女。","is_first_visit":false,"new_site_to_vu_count":0,"followers_count":2817,"location":"","small_avatar":"http:\/\/img3.douban.com\/icon\/u2191713-36.jpg","following":false,"verified":false,"large_avatar":"http:\/\/img3.douban.com\/icon\/ul2191713-36.jpg","type":"user","id":"2191713","uid":"tealove"},{"city":"","icon_avatar":"http:\/\/img3.douban.com\/icon\/ui56023193-37.jpg","statuses_count":355,"screen_name":"_S","following_count":132,"url":"http:\/\/www.douban.com\/people\/56023193\/","created_at":"2011-11-14 14:11:43","description":"","is_first_visit":false,"new_site_to_vu_count":2,"followers_count":28,"location":"","small_avatar":"http:\/\/img3.douban.com\/icon\/u56023193-37.jpg","following":false,"verified":false,"large_avatar":"http:\/\/img3.douban.com\/icon\/ul56023193-37.jpg","type":"user","id":"56023193","uid":"sevinomaxiao"},{"city":"","icon_avatar":"http:\/\/img3.douban.com\/icon\/ui47489622-6.jpg","statuses_count":148,"screen_name":"花轮和彦","following_count":1269,"url":"http:\/\/www.douban.com\/people\/47489622\/","created_at":"2010-11-18 21:56:50","description":"","is_first_visit":false,"new_site_to_vu_count":0,"followers_count":764,"location":"","small_avatar":"http:\/\/img3.douban.com\/icon\/u47489622-6.jpg","following":false,"verified":false,"large_avatar":"http:\/\/img3.douban.com\/icon\/ul47489622-6.jpg","type":"user","id":"47489622","uid":"hualunlun"},{"city":"","icon_avatar":"http:\/\/img3.douban.com\/icon\/ui28302337-1.jpg","statuses_count":439,"screen_name":"修江逐潮","following_count":126,"url":"http:\/\/www.douban.com\/people\/28302337\/","created_at":"2009-12-09 12:16:49","description":"","is_first_visit":false,"new_site_to_vu_count":0,"followers_count":115,"location":"","small_avatar":"http:\/\/img3.douban.com\/icon\/u28302337-1.jpg","following":false,"verified":false,"large_avatar":"http:\/\/img3.douban.com\/icon\/ul28302337-1.jpg","type":"user","id":"28302337","uid":"zhu.chao"}]
